{
    "authors": {
        "Author": [
            "MachineMuse"
        ]
    },
    "categories": [
        "API"
    ],
    "description": "",
    "iconUrl": "",
    "logoUrl": "",
    "modId": "numina",
    "name": "Numina",
    "nemName": "",
    "references": {
    },
    "tags": [
    ],
    "uid": "",
    "updateUrl": "https://raw.github.com/02JanDal/QuickMod/master/Numina.json",
    "versionsUrl": "https://raw.github.com/02JanDal/QuickMod/master/Numina.versions.json",
    "websiteUrl": "https://github.com/MachineMuse/Numina"
}
