[
    {
        "downloadType": "parallel",
        "installType": "forgeMod",
        "mcCompat": [
            "1.6.4"
        ],
        "md5": "f77a1f5217f2d89b0d319e50ca2520b0",
        "name": "1.5.3",
        "references": [
        ],
        "url": "http://www.curse.com/mc-mods/minecraft/tinkers-construct/775458"
    },
    {
        "downloadType": "parallel",
        "installType": "forgeMod",
        "mcCompat": [
            "1.6.4"
        ],
        "md5": "8ed1c59dac06cbdc8808d4364f6d0774",
        "name": "1.5.2.6",
        "references": [
        ],
        "url": "http://www.curse.com/mc-mods/minecraft/tinkers-construct/772402"
    }
]
